Metadata-Version: 1.1
Name: facebook-api-wrapper
Version: 0.0.2
Summary: A python package that can be installed with pip.
Home-page: https://github.com/mr.ehbr/facebook_api
Author: mr.Ehbr
Author-email: mr.ehbr@gmail.com
License: BSD
Download-URL: https://github.com/mr.ehbr/facebook_api/tarball/0.0.2
Platform: UNKNOWN
Classifier: Development Status :: 3 - Alpha
Classifier: Intended Audience :: Developers
Classifier: Programming Language :: Python :: 3
